wolfpackmaker/__init__.py
wolfpackmaker/__main__.py
wolfpackmaker/wolfpackmaker.py
wolfpackmaker/launchers/__init__.py
wolfpackmaker/launchers/multimc.py
wolfpackmaker-2.0.11.data/scripts/wolfpackmaker
wolfpackmaker-2.0.11.dist-info/METADATA
wolfpackmaker-2.0.11.dist-info/WHEEL
wolfpackmaker-2.0.11.dist-info/top_level.txt
wolfpackmaker-2.0.11.dist-info/RECORD
