Metadata-Version: 2.1
Name: wolfpackmaker
Version: 2.0.11
Summary: Python script helper to download WolfpackMC modpack resources for client launching. https://github.com/WolfpackMC
Home-page: https://github.com/WolfpackMC/wolfpackmaker
Author: Kalka
Author-email: kalka2088@gmail.com
License: UNKNOWN
Project-URL: Bug Tracker, https://github.com/WolfpackMC/wolfpackmaker/issues
Platform: UNKNOWN
Requires-Python: >=3.10
Requires-Dist: wolfpackutil
